pyqgssim/__init__.py
pyqgssim/cli.py
pyqgssim/config.py
pyqgssim/assets/config.toml
pyqgssim/assets/fontawesome-webfont.ttf
pyqgssim/assets/main.ico
pyqgssim/assets/main.qrc
pyqgssim/assets/main.rc
pyqgssim/assets/main_rc.py
pyqgssim/assets/qss.qrc
pyqgssim/assets/qss_rc.py
pyqgssim/assets/qt_zh_CN.qm
pyqgssim/assets/widgets.qm
pyqgssim/assets/image/mw.png
pyqgssim/assets/image/gif/picture.gif
pyqgssim/assets/image/icon/0.ico
pyqgssim/assets/image/icon/1.ico
pyqgssim/assets/image/icon/2.ico
pyqgssim/assets/image/icon/3.ico
pyqgssim/assets/image/icon/4.ico
pyqgssim/assets/image/icon/5.ico
pyqgssim/assets/image/icon/6.ico
pyqgssim/assets/image/icon/Ar1.ico
pyqgssim/assets/image/icon/Ar10.ico
pyqgssim/assets/image/icon/Ar11.ico
pyqgssim/assets/image/icon/Ar12.ico
pyqgssim/assets/image/icon/Ar13.ico
pyqgssim/assets/image/icon/Ar14.ico
pyqgssim/assets/image/icon/Ar15.ico
pyqgssim/assets/image/icon/Ar16.ico
pyqgssim/assets/image/icon/Ar17.ico
pyqgssim/assets/image/icon/Ar18.ico
pyqgssim/assets/image/icon/Ar19.ico
pyqgssim/assets/image/icon/Ar2.ico
pyqgssim/assets/image/icon/Ar20.ico
pyqgssim/assets/image/icon/Ar21.ico
pyqgssim/assets/image/icon/Ar22.ico
pyqgssim/assets/image/icon/Ar23.ico
pyqgssim/assets/image/icon/Ar24.ico
pyqgssim/assets/image/icon/Ar25.ico
pyqgssim/assets/image/icon/Ar26.ico
pyqgssim/assets/image/icon/Ar27.ico
pyqgssim/assets/image/icon/Ar3.ico
pyqgssim/assets/image/icon/Ar4.ico
pyqgssim/assets/image/icon/Ar5.ico
pyqgssim/assets/image/icon/Ar6.ico
pyqgssim/assets/image/icon/Ar7.ico
pyqgssim/assets/image/icon/Ar8.ico
pyqgssim/assets/image/icon/Ar9.ico
pyqgssim/assets/image/icon/a1.ico
pyqgssim/assets/image/icon/a10.ico
pyqgssim/assets/image/icon/a11.ico
pyqgssim/assets/image/icon/a12.ico
pyqgssim/assets/image/icon/a13.ico
pyqgssim/assets/image/icon/a14.ico
pyqgssim/assets/image/icon/a15.ico
pyqgssim/assets/image/icon/a16.ico
pyqgssim/assets/image/icon/a17.ico
pyqgssim/assets/image/icon/a18.ico
pyqgssim/assets/image/icon/a19.ico
pyqgssim-0.1.1.dist-info/METADATA
pyqgssim-0.1.1.dist-info/WHEEL
pyqgssim-0.1.1.dist-info/entry_points.txt
pyqgssim-0.1.1.dist-info/licenses/AUTHORS.rst
pyqgssim-0.1.1.dist-info/licenses/LICENSE
pyqgssim-0.1.1.dist-info/RECORD
